{"_class":"page","do_objectID":"a4586046-e2f7-4519-b904-f3638e0aa03d","exportOptions":{"_class":"exportOptions","exportFormats":[],"includedLayerIds":[],"layerOptions":0,"shouldTrim":false},"isFlippedHorizontal":false,"isFlippedVertical":false,"isLocked":false,"isVisible":true,"layerListExpandedType":0,"name":"page","nameIsFixed":false,"resizingConstraint":63,"resizingType":0,"rotation":0,"shouldBreakMaskChain":false,"layers":[{"_class":"artboard","do_objectID":"23148e4f-cf3e-491a-9882-cd39167b62a8","exportOptions":{"_class":"exportOptions","exportFormats":[],"includedLayerIds":[],"layerOptions":0,"shouldTrim":false},"isFlippedHorizontal":false,"isFlippedVertical":false,"isLocked":false,"isVisible":true,"layerListExpandedType":0,"name":"artboard","nameIsFixed":false,"resizingConstraint":63,"resizingType":0,"rotation":0,"shouldBreakMaskChain":false,"layers":[{"_class":"group","do_objectID":"d413abb6-81fb-4591-bb03-6dba0a4930ae","exportOptions":{"_class":"exportOptions","exportFormats":[],"includedLayerIds":[],"layerOptions":0,"shouldTrim":false},"isFlippedHorizontal":false,"isFlippedVertical":false,"isLocked":false,"isVisible":true,"layerListExpandedType":0,"name":"(body)","nameIsFixed":false,"resizingConstraint":63,"resizingType":0,"rotation":0,"shouldBreakMaskChain":false,"layers":[{"_class":"group","do_objectID":"07a5429c-c50d-48c6-af63-bde2feabebdb","exportOptions":{"_class":"exportOptions","exportFormats":[],"includedLayerIds":[],"layerOptions":0,"shouldTrim":false},"isFlippedHorizontal":false,"isFlippedVertical":false,"isLocked":false,"isVisible":true,"layerListExpandedType":0,"name":"(stellar-avatar)","nameIsFixed":false,"resizingConstraint":63,"resizingType":0,"rotation":0,"shouldBreakMaskChain":false,"layers":[],"clippingMaskMode":0,"hasClippingMask":false,"style":{"_class":"style","fills":[],"borders":[],"shadows":[],"innerShadows":[],"endDecorationType":0,"miterLimit":10,"startDecorationType":0,"contextSettings":{"_class":"graphicsContextSettings","blendMode":0,"opacity":"1"}},"frame":{"_class":"rect","constrainProportions":false,"height":28.15625,"width":28.15625,"x":0,"y":98.5625},"hasClickThrough":false,"windingRule":1},{"_class":"group","do_objectID":"cdb2c49b-3021-4536-8c2a-f2cb82522abc","exportOptions":{"_class":"exportOptions","exportFormats":[],"includedLayerIds":[],"layerOptions":0,"shouldTrim":false},"isFlippedHorizontal":false,"isFlippedVertical":false,"isLocked":false,"isVisible":true,"layerListExpandedType":0,"name":"(button)","nameIsFixed":false,"resizingConstraint":63,"resizingType":0,"rotation":0,"shouldBreakMaskChain":false,"layers":[{"_class":"group","do_objectID":"50703fcc-f8b4-40ad-91d3-d4c9a3501035","exportOptions":{"_class":"exportOptions","exportFormats":[],"includedLayerIds":[],"layerOptions":0,"shouldTrim":false},"isFlippedHorizontal":false,"isFlippedVertical":false,"isLocked":false,"isVisible":true,"layerListExpandedType":0,"name":"(div)","nameIsFixed":false,"resizingConstraint":63,"resizingType":0,"rotation":0,"shouldBreakMaskChain":false,"layers":[{"_class":"group","do_objectID":"7d5de4cc-b507-47f7-8a76-953ee4b40abb","exportOptions":{"_class":"exportOptions","exportFormats":[],"includedLayerIds":[],"layerOptions":0,"shouldTrim":false},"isFlippedHorizontal":false,"isFlippedVertical":false,"isLocked":false,"isVisible":true,"layerListExpandedType":0,"name":"(div)","nameIsFixed":false,"resizingConstraint":63,"resizingType":0,"rotation":0,"shouldBreakMaskChain":false,"layers":[{"_class":"shapeGroup","do_objectID":"fdba3031-9c7d-4cfc-8c21-454b0414e1b5","exportOptions":{"_class":"exportOptions","exportFormats":[],"includedLayerIds":[],"layerOptions":0,"shouldTrim":false},"isFlippedHorizontal":false,"isFlippedVertical":false,"isLocked":false,"isVisible":true,"layerListExpandedType":0,"name":"/button[@class=\"wrapper\"]/div[@class=\"content\"]/div[@class=\"spacer\"]","nameIsFixed":false,"resizingConstraint":63,"resizingType":0,"rotation":0,"shouldBreakMaskChain":false,"layers":[{"_class":"rectangle","do_objectID":"a5669aad-eee0-456f-a1e6-dc93383275e0","exportOptions":{"_class":"exportOptions","exportFormats":[],"includedLayerIds":[],"layerOptions":0,"shouldTrim":false},"isFlippedHorizontal":false,"isFlippedVertical":false,"isLocked":false,"isVisible":true,"layerListExpandedType":0,"name":"rectangle","nameIsFixed":false,"resizingConstraint":63,"resizingType":0,"rotation":0,"shouldBreakMaskChain":false,"layers":[],"clippingMaskMode":0,"hasClippingMask":false,"frame":{"_class":"rect","constrainProportions":false,"height":28.15625,"width":28.15625,"x":0,"y":0},"path":{"_class":"path","isClosed":true,"pointRadiusBehaviour":1,"points":[{"_class":"curvePoint","cornerRadius":0,"curveFrom":"{0, 0}","curveMode":1,"curveTo":"{0, 0}","hasCurveFrom":false,"hasCurveTo":false,"point":"{0, 0}"},{"_class":"curvePoint","cornerRadius":0,"curveFrom":"{1, 0}","curveMode":1,"curveTo":"{1, 0}","hasCurveFrom":false,"hasCurveTo":false,"point":"{1, 0}"},{"_class":"curvePoint","cornerRadius":0,"curveFrom":"{1, 1}","curveMode":1,"curveTo":"{1, 1}","hasCurveFrom":false,"hasCurveTo":false,"point":"{1, 1}"},{"_class":"curvePoint","cornerRadius":0,"curveFrom":"{0, 1}","curveMode":1,"curveTo":"{0, 1}","hasCurveFrom":false,"hasCurveTo":false,"point":"{0, 1}"}]},"hasConvertedToNewRoundCorners":true,"fixedRadius":0,"edited":false,"booleanOperation":-1}],"clippingMaskMode":0,"hasClippingMask":false,"style":{"_class":"style","fills":[{"_class":"fill","isEnabled":true,"color":{"_class":"color","red":0,"green":0,"blue":0,"alpha":0},"fillType":0,"noiseIndex":0,"noiseIntensity":0,"patternFillType":1,"patternTileScale":1},{"_class":"fill","isEnabled":true,"color":{"_class":"color","alpha":1,"blue":0.847,"green":0.847,"red":0.847},"fillType":1,"gradient":{"_class":"gradient","elipseLength":0,"from":"{0.5, 0","gradientType":0,"shouldSmoothenOpacity":false,"stops":[{"_class":"gradientStop","color":{"_class":"color","red":0.792156862745098,"green":0.27450980392156865,"blue":0.29411764705882354,"alpha":1},"position":0},{"_class":"gradientStop","color":{"_class":"color","red":1,"green":0.34901960784313724,"blue":0.37254901960784315,"alpha":1},"position":1}],"to":"{0.5, 1}"},"noiseIndex":0,"noiseIntensity":0,"patternFillType":1,"patternTileScale":1}],"borders":[{"_class":"border","isEnabled":true,"color":{"_class":"color","red":0,"green":0,"blue":0,"alpha":0.8470588235294118},"fillType":0,"position":1,"thickness":0}],"shadows":[],"innerShadows":[],"endDecorationType":0,"miterLimit":10,"startDecorationType":0,"contextSettings":{"_class":"graphicsContextSettings","blendMode":0,"opacity":"1"}},"frame":{"_class":"rect","constrainProportions":false,"height":28.15625,"width":28.15625,"x":0,"y":0},"hasClickThrough":false,"windingRule":1}],"clippingMaskMode":0,"hasClippingMask":false,"style":{"_class":"style","fills":[],"borders":[],"shadows":[],"innerShadows":[],"endDecorationType":0,"miterLimit":10,"startDecorationType":0,"contextSettings":{"_class":"graphicsContextSettings","blendMode":0,"opacity":"1"}},"frame":{"_class":"rect","constrainProportions":false,"height":28.15625,"width":28.15625,"x":0,"y":0},"hasClickThrough":false,"windingRule":1},{"_class":"group","do_objectID":"7836824c-d8c6-46e2-aeda-68f90d6ae81d","exportOptions":{"_class":"exportOptions","exportFormats":[],"includedLayerIds":[],"layerOptions":0,"shouldTrim":false},"isFlippedHorizontal":false,"isFlippedVertical":false,"isLocked":false,"isVisible":true,"layerListExpandedType":0,"name":"(div)","nameIsFixed":false,"resizingConstraint":63,"resizingType":0,"rotation":0,"shouldBreakMaskChain":false,"layers":[{"_class":"text","do_objectID":"f59fc870-c30c-4790-a4a6-ccb2bfd90cc2","exportOptions":{"_class":"exportOptions","exportFormats":[],"includedLayerIds":[],"layerOptions":0,"shouldTrim":false},"isFlippedHorizontal":false,"isFlippedVertical":false,"isLocked":false,"isVisible":true,"layerListExpandedType":0,"name":"W","nameIsFixed":false,"resizingConstraint":47,"resizingType":0,"rotation":0,"shouldBreakMaskChain":false,"clippingMaskMode":0,"hasClippingMask":false,"style":{"color":"rgb(255, 255, 255)","fontSize":12,"fontFamily":"-apple-system","fontWeight":600,"lineHeight":12,"textDecoration":"none","textAlign":"center","textTransform":"lowercase"},"frame":{"_class":"rect","constrainProportions":false,"height":15,"width":10.4375,"x":8.84375,"y":8.53125},"text":"W","automaticallyDrawOnUnderlyingPath":false,"dontSynchroniseWithSymbol":false,"lineSpacingBehaviour":2,"textBehaviour":0}],"clippingMaskMode":0,"hasClippingMask":false,"style":{"_class":"style","fills":[],"borders":[],"shadows":[],"innerShadows":[],"endDecorationType":0,"miterLimit":10,"startDecorationType":0,"contextSettings":{"_class":"graphicsContextSettings","blendMode":0,"opacity":"1"}},"frame":{"_class":"rect","constrainProportions":false,"height":28.15625,"width":28.15625,"x":0,"y":0},"hasClickThrough":false,"windingRule":1}],"clippingMaskMode":0,"hasClippingMask":false,"style":{"_class":"style","fills":[],"borders":[],"shadows":[],"innerShadows":[],"endDecorationType":0,"miterLimit":10,"startDecorationType":0,"contextSettings":{"_class":"graphicsContextSettings","blendMode":0,"opacity":"1"}},"frame":{"_class":"rect","constrainProportions":false,"height":28.15625,"width":28.15625,"x":0,"y":0},"hasClickThrough":false,"windingRule":1}],"clippingMaskMode":0,"hasClippingMask":false,"style":{"_class":"style","fills":[],"borders":[],"shadows":[],"innerShadows":[],"endDecorationType":0,"miterLimit":10,"startDecorationType":0,"contextSettings":{"_class":"graphicsContextSettings","blendMode":0,"opacity":"1"}},"frame":{"_class":"rect","constrainProportions":false,"height":28.15625,"width":28.15625,"x":0,"y":98.5625},"hasClickThrough":false,"windingRule":1},{"_class":"group","do_objectID":"bc8acd14-8d4f-4974-a0ac-94505e11d18b","exportOptions":{"_class":"exportOptions","exportFormats":[],"includedLayerIds":[],"layerOptions":0,"shouldTrim":false},"isFlippedHorizontal":false,"isFlippedVertical":false,"isLocked":false,"isVisible":true,"layerListExpandedType":0,"name":"(stellar-avatar)","nameIsFixed":false,"resizingConstraint":63,"resizingType":0,"rotation":0,"shouldBreakMaskChain":false,"layers":[],"clippingMaskMode":0,"hasClippingMask":false,"style":{"_class":"style","fills":[],"borders":[],"shadows":[],"innerShadows":[],"endDecorationType":0,"miterLimit":10,"startDecorationType":0,"contextSettings":{"_class":"graphicsContextSettings","blendMode":0,"opacity":"1"}},"frame":{"_class":"rect","constrainProportions":false,"height":35.1875,"width":35.1875,"x":28.15625,"y":91.53125},"hasClickThrough":false,"windingRule":1},{"_class":"group","do_objectID":"1a9f0409-912b-4079-a1db-85e11fc81b88","exportOptions":{"_class":"exportOptions","exportFormats":[],"includedLayerIds":[],"layerOptions":0,"shouldTrim":false},"isFlippedHorizontal":false,"isFlippedVertical":false,"isLocked":false,"isVisible":true,"layerListExpandedType":0,"name":"(button)","nameIsFixed":false,"resizingConstraint":63,"resizingType":0,"rotation":0,"shouldBreakMaskChain":false,"layers":[{"_class":"group","do_objectID":"43c375ae-ccbe-45aa-b190-db3d5c50b6b9","exportOptions":{"_class":"exportOptions","exportFormats":[],"includedLayerIds":[],"layerOptions":0,"shouldTrim":false},"isFlippedHorizontal":false,"isFlippedVertical":false,"isLocked":false,"isVisible":true,"layerListExpandedType":0,"name":"(div)","nameIsFixed":false,"resizingConstraint":63,"resizingType":0,"rotation":0,"shouldBreakMaskChain":false,"layers":[{"_class":"group","do_objectID":"975c191b-1bf0-4993-8683-300b3eaf5707","exportOptions":{"_class":"exportOptions","exportFormats":[],"includedLayerIds":[],"layerOptions":0,"shouldTrim":false},"isFlippedHorizontal":false,"isFlippedVertical":false,"isLocked":false,"isVisible":true,"layerListExpandedType":0,"name":"(div)","nameIsFixed":false,"resizingConstraint":63,"resizingType":0,"rotation":0,"shouldBreakMaskChain":false,"layers":[{"_class":"shapeGroup","do_objectID":"38f88159-7934-4608-ac2c-d6070db96c89","exportOptions":{"_class":"exportOptions","exportFormats":[],"includedLayerIds":[],"layerOptions":0,"shouldTrim":false},"isFlippedHorizontal":false,"isFlippedVertical":false,"isLocked":false,"isVisible":true,"layerListExpandedType":0,"name":"/button[@class=\"wrapper\"]/div[@class=\"content\"]/div[@class=\"spacer\"]","nameIsFixed":false,"resizingConstraint":63,"resizingType":0,"rotation":0,"shouldBreakMaskChain":false,"layers":[{"_class":"rectangle","do_objectID":"575caaa2-00b4-492b-be6c-f1d6f5ce1f86","exportOptions":{"_class":"exportOptions","exportFormats":[],"includedLayerIds":[],"layerOptions":0,"shouldTrim":false},"isFlippedHorizontal":false,"isFlippedVertical":false,"isLocked":false,"isVisible":true,"layerListExpandedType":0,"name":"rectangle","nameIsFixed":false,"resizingConstraint":63,"resizingType":0,"rotation":0,"shouldBreakMaskChain":false,"layers":[],"clippingMaskMode":0,"hasClippingMask":false,"frame":{"_class":"rect","constrainProportions":false,"height":35.1875,"width":35.1875,"x":0,"y":0},"path":{"_class":"path","isClosed":true,"pointRadiusBehaviour":1,"points":[{"_class":"curvePoint","cornerRadius":0,"curveFrom":"{0, 0}","curveMode":1,"curveTo":"{0, 0}","hasCurveFrom":false,"hasCurveTo":false,"point":"{0, 0}"},{"_class":"curvePoint","cornerRadius":0,"curveFrom":"{1, 0}","curveMode":1,"curveTo":"{1, 0}","hasCurveFrom":false,"hasCurveTo":false,"point":"{1, 0}"},{"_class":"curvePoint","cornerRadius":0,"curveFrom":"{1, 1}","curveMode":1,"curveTo":"{1, 1}","hasCurveFrom":false,"hasCurveTo":false,"point":"{1, 1}"},{"_class":"curvePoint","cornerRadius":0,"curveFrom":"{0, 1}","curveMode":1,"curveTo":"{0, 1}","hasCurveFrom":false,"hasCurveTo":false,"point":"{0, 1}"}]},"hasConvertedToNewRoundCorners":true,"fixedRadius":0,"edited":false,"booleanOperation":-1}],"clippingMaskMode":0,"hasClippingMask":false,"style":{"_class":"style","fills":[{"_class":"fill","isEnabled":true,"color":{"_class":"color","red":0,"green":0,"blue":0,"alpha":0},"fillType":0,"noiseIndex":0,"noiseIntensity":0,"patternFillType":1,"patternTileScale":1},{"_class":"fill","isEnabled":true,"color":{"_class":"color","alpha":1,"blue":0.847,"green":0.847,"red":0.847},"fillType":1,"gradient":{"_class":"gradient","elipseLength":0,"from":"{0.5, 0","gradientType":0,"shouldSmoothenOpacity":false,"stops":[{"_class":"gradientStop","color":{"_class":"color","red":0.792156862745098,"green":0.27450980392156865,"blue":0.29411764705882354,"alpha":1},"position":0},{"_class":"gradientStop","color":{"_class":"color","red":1,"green":0.34901960784313724,"blue":0.37254901960784315,"alpha":1},"position":1}],"to":"{0.5, 1}"},"noiseIndex":0,"noiseIntensity":0,"patternFillType":1,"patternTileScale":1}],"borders":[{"_class":"border","isEnabled":true,"color":{"_class":"color","red":0,"green":0,"blue":0,"alpha":0.8470588235294118},"fillType":0,"position":1,"thickness":0}],"shadows":[],"innerShadows":[],"endDecorationType":0,"miterLimit":10,"startDecorationType":0,"contextSettings":{"_class":"graphicsContextSettings","blendMode":0,"opacity":"1"}},"frame":{"_class":"rect","constrainProportions":false,"height":35.1875,"width":35.1875,"x":0,"y":0},"hasClickThrough":false,"windingRule":1}],"clippingMaskMode":0,"hasClippingMask":false,"style":{"_class":"style","fills":[],"borders":[],"shadows":[],"innerShadows":[],"endDecorationType":0,"miterLimit":10,"startDecorationType":0,"contextSettings":{"_class":"graphicsContextSettings","blendMode":0,"opacity":"1"}},"frame":{"_class":"rect","constrainProportions":false,"height":35.1875,"width":35.1875,"x":0,"y":0},"hasClickThrough":false,"windingRule":1},{"_class":"group","do_objectID":"bb753f08-68fb-494f-95f6-df6d81b25962","exportOptions":{"_class":"exportOptions","exportFormats":[],"includedLayerIds":[],"layerOptions":0,"shouldTrim":false},"isFlippedHorizontal":false,"isFlippedVertical":false,"isLocked":false,"isVisible":true,"layerListExpandedType":0,"name":"(div)","nameIsFixed":false,"resizingConstraint":63,"resizingType":0,"rotation":0,"shouldBreakMaskChain":false,"layers":[{"_class":"text","do_objectID":"27cb9b2f-a80e-454e-8ed4-612635a1e8f3","exportOptions":{"_class":"exportOptions","exportFormats":[],"includedLayerIds":[],"layerOptions":0,"shouldTrim":false},"isFlippedHorizontal":false,"isFlippedVertical":false,"isLocked":false,"isVisible":true,"layerListExpandedType":0,"name":"W","nameIsFixed":false,"resizingConstraint":47,"resizingType":0,"rotation":0,"shouldBreakMaskChain":false,"clippingMaskMode":0,"hasClippingMask":false,"style":{"color":"rgb(255, 255, 255)","fontSize":16,"fontFamily":"-apple-system","fontWeight":600,"lineHeight":16,"textDecoration":"none","textAlign":"center","textTransform":"lowercase"},"frame":{"_class":"rect","constrainProportions":false,"height":18,"width":12.8125,"x":11.171875,"y":10.796875},"text":"W","automaticallyDrawOnUnderlyingPath":false,"dontSynchroniseWithSymbol":false,"lineSpacingBehaviour":2,"textBehaviour":0}],"clippingMaskMode":0,"hasClippingMask":false,"style":{"_class":"style","fills":[],"borders":[],"shadows":[],"innerShadows":[],"endDecorationType":0,"miterLimit":10,"startDecorationType":0,"contextSettings":{"_class":"graphicsContextSettings","blendMode":0,"opacity":"1"}},"frame":{"_class":"rect","constrainProportions":false,"height":35.1875,"width":35.1875,"x":0,"y":0},"hasClickThrough":false,"windingRule":1}],"clippingMaskMode":0,"hasClippingMask":false,"style":{"_class":"style","fills":[],"borders":[],"shadows":[],"innerShadows":[],"endDecorationType":0,"miterLimit":10,"startDecorationType":0,"contextSettings":{"_class":"graphicsContextSettings","blendMode":0,"opacity":"1"}},"frame":{"_class":"rect","constrainProportions":false,"height":35.1875,"width":35.1875,"x":0,"y":0},"hasClickThrough":false,"windingRule":1}],"clippingMaskMode":0,"hasClippingMask":false,"style":{"_class":"style","fills":[],"borders":[],"shadows":[],"innerShadows":[],"endDecorationType":0,"miterLimit":10,"startDecorationType":0,"contextSettings":{"_class":"graphicsContextSettings","blendMode":0,"opacity":"1"}},"frame":{"_class":"rect","constrainProportions":false,"height":35.1875,"width":35.1875,"x":28.15625,"y":91.53125},"hasClickThrough":false,"windingRule":1},{"_class":"group","do_objectID":"c7052689-3cd9-4059-900c-5ab80eb16c66","exportOptions":{"_class":"exportOptions","exportFormats":[],"includedLayerIds":[],"layerOptions":0,"shouldTrim":false},"isFlippedHorizontal":false,"isFlippedVertical":false,"isLocked":false,"isVisible":true,"layerListExpandedType":0,"name":"(stellar-avatar)","nameIsFixed":false,"resizingConstraint":63,"resizingType":0,"rotation":0,"shouldBreakMaskChain":false,"layers":[],"clippingMaskMode":0,"hasClippingMask":false,"style":{"_class":"style","fills":[],"borders":[],"shadows":[],"innerShadows":[],"endDecorationType":0,"miterLimit":10,"startDecorationType":0,"contextSettings":{"_class":"graphicsContextSettings","blendMode":0,"opacity":"1"}},"frame":{"_class":"rect","constrainProportions":false,"height":63.359375,"width":63.359375,"x":63.34375,"y":63.359375},"hasClickThrough":false,"windingRule":1},{"_class":"group","do_objectID":"07f75354-0485-49aa-a146-79afa36c4557","exportOptions":{"_class":"exportOptions","exportFormats":[],"includedLayerIds":[],"layerOptions":0,"shouldTrim":false},"isFlippedHorizontal":false,"isFlippedVertical":false,"isLocked":false,"isVisible":true,"layerListExpandedType":0,"name":"(button)","nameIsFixed":false,"resizingConstraint":63,"resizingType":0,"rotation":0,"shouldBreakMaskChain":false,"layers":[{"_class":"group","do_objectID":"8b0a77d9-3ecc-4e10-8402-58ab8e67fa7c","exportOptions":{"_class":"exportOptions","exportFormats":[],"includedLayerIds":[],"layerOptions":0,"shouldTrim":false},"isFlippedHorizontal":false,"isFlippedVertical":false,"isLocked":false,"isVisible":true,"layerListExpandedType":0,"name":"(div)","nameIsFixed":false,"resizingConstraint":63,"resizingType":0,"rotation":0,"shouldBreakMaskChain":false,"layers":[{"_class":"group","do_objectID":"4a6d6671-307d-4804-b8b6-e0699ef0f322","exportOptions":{"_class":"exportOptions","exportFormats":[],"includedLayerIds":[],"layerOptions":0,"shouldTrim":false},"isFlippedHorizontal":false,"isFlippedVertical":false,"isLocked":false,"isVisible":true,"layerListExpandedType":0,"name":"(div)","nameIsFixed":false,"resizingConstraint":63,"resizingType":0,"rotation":0,"shouldBreakMaskChain":false,"layers":[{"_class":"shapeGroup","do_objectID":"3a187bb8-4320-43bb-8dd2-8665c140c1bf","exportOptions":{"_class":"exportOptions","exportFormats":[],"includedLayerIds":[],"layerOptions":0,"shouldTrim":false},"isFlippedHorizontal":false,"isFlippedVertical":false,"isLocked":false,"isVisible":true,"layerListExpandedType":0,"name":"/button[@class=\"wrapper\"]/div[@class=\"content\"]/div[@class=\"spacer\"]","nameIsFixed":false,"resizingConstraint":63,"resizingType":0,"rotation":0,"shouldBreakMaskChain":false,"layers":[{"_class":"rectangle","do_objectID":"f5a1d620-7854-41a3-b43d-0339efa45fed","exportOptions":{"_class":"exportOptions","exportFormats":[],"includedLayerIds":[],"layerOptions":0,"shouldTrim":false},"isFlippedHorizontal":false,"isFlippedVertical":false,"isLocked":false,"isVisible":true,"layerListExpandedType":0,"name":"rectangle","nameIsFixed":false,"resizingConstraint":63,"resizingType":0,"rotation":0,"shouldBreakMaskChain":false,"layers":[],"clippingMaskMode":0,"hasClippingMask":false,"frame":{"_class":"rect","constrainProportions":false,"height":63.359375,"width":63.359375,"x":0,"y":0},"path":{"_class":"path","isClosed":true,"pointRadiusBehaviour":1,"points":[{"_class":"curvePoint","cornerRadius":0,"curveFrom":"{0, 0}","curveMode":1,"curveTo":"{0, 0}","hasCurveFrom":false,"hasCurveTo":false,"point":"{0, 0}"},{"_class":"curvePoint","cornerRadius":0,"curveFrom":"{1, 0}","curveMode":1,"curveTo":"{1, 0}","hasCurveFrom":false,"hasCurveTo":false,"point":"{1, 0}"},{"_class":"curvePoint","cornerRadius":0,"curveFrom":"{1, 1}","curveMode":1,"curveTo":"{1, 1}","hasCurveFrom":false,"hasCurveTo":false,"point":"{1, 1}"},{"_class":"curvePoint","cornerRadius":0,"curveFrom":"{0, 1}","curveMode":1,"curveTo":"{0, 1}","hasCurveFrom":false,"hasCurveTo":false,"point":"{0, 1}"}]},"hasConvertedToNewRoundCorners":true,"fixedRadius":0,"edited":false,"booleanOperation":-1}],"clippingMaskMode":0,"hasClippingMask":false,"style":{"_class":"style","fills":[{"_class":"fill","isEnabled":true,"color":{"_class":"color","red":0,"green":0,"blue":0,"alpha":0},"fillType":0,"noiseIndex":0,"noiseIntensity":0,"patternFillType":1,"patternTileScale":1},{"_class":"fill","isEnabled":true,"color":{"_class":"color","alpha":1,"blue":0.847,"green":0.847,"red":0.847},"fillType":1,"gradient":{"_class":"gradient","elipseLength":0,"from":"{0.5, 0","gradientType":0,"shouldSmoothenOpacity":false,"stops":[{"_class":"gradientStop","color":{"_class":"color","red":0.792156862745098,"green":0.27450980392156865,"blue":0.29411764705882354,"alpha":1},"position":0},{"_class":"gradientStop","color":{"_class":"color","red":1,"green":0.34901960784313724,"blue":0.37254901960784315,"alpha":1},"position":1}],"to":"{0.5, 1}"},"noiseIndex":0,"noiseIntensity":0,"patternFillType":1,"patternTileScale":1}],"borders":[{"_class":"border","isEnabled":true,"color":{"_class":"color","red":0,"green":0,"blue":0,"alpha":0.8470588235294118},"fillType":0,"position":1,"thickness":0}],"shadows":[],"innerShadows":[],"endDecorationType":0,"miterLimit":10,"startDecorationType":0,"contextSettings":{"_class":"graphicsContextSettings","blendMode":0,"opacity":"1"}},"frame":{"_class":"rect","constrainProportions":false,"height":63.359375,"width":63.359375,"x":0,"y":0},"hasClickThrough":false,"windingRule":1}],"clippingMaskMode":0,"hasClippingMask":false,"style":{"_class":"style","fills":[],"borders":[],"shadows":[],"innerShadows":[],"endDecorationType":0,"miterLimit":10,"startDecorationType":0,"contextSettings":{"_class":"graphicsContextSettings","blendMode":0,"opacity":"1"}},"frame":{"_class":"rect","constrainProportions":false,"height":63.359375,"width":63.359375,"x":0,"y":0},"hasClickThrough":false,"windingRule":1},{"_class":"group","do_objectID":"0a2aaae4-fd4f-4754-b2a3-d5499617b3d6","exportOptions":{"_class":"exportOptions","exportFormats":[],"includedLayerIds":[],"layerOptions":0,"shouldTrim":false},"isFlippedHorizontal":false,"isFlippedVertical":false,"isLocked":false,"isVisible":true,"layerListExpandedType":0,"name":"(div)","nameIsFixed":false,"resizingConstraint":63,"resizingType":0,"rotation":0,"shouldBreakMaskChain":false,"layers":[{"_class":"text","do_objectID":"37c99e53-3a01-4f94-902c-e5afeb4ef34e","exportOptions":{"_class":"exportOptions","exportFormats":[],"includedLayerIds":[],"layerOptions":0,"shouldTrim":false},"isFlippedHorizontal":false,"isFlippedVertical":false,"isLocked":false,"isVisible":true,"layerListExpandedType":0,"name":"WM","nameIsFixed":false,"resizingConstraint":47,"resizingType":0,"rotation":0,"shouldBreakMaskChain":false,"clippingMaskMode":0,"hasClippingMask":false,"style":{"color":"rgb(255, 255, 255)","fontSize":28,"fontFamily":"-apple-system","fontWeight":600,"lineHeight":28,"textDecoration":"none","textAlign":"center","textTransform":"lowercase"},"frame":{"_class":"rect","constrainProportions":false,"height":34,"width":46.921875,"x":8.21875,"y":19.84375},"text":"WM","automaticallyDrawOnUnderlyingPath":false,"dontSynchroniseWithSymbol":false,"lineSpacingBehaviour":2,"textBehaviour":0}],"clippingMaskMode":0,"hasClippingMask":false,"style":{"_class":"style","fills":[],"borders":[],"shadows":[],"innerShadows":[],"endDecorationType":0,"miterLimit":10,"startDecorationType":0,"contextSettings":{"_class":"graphicsContextSettings","blendMode":0,"opacity":"1"}},"frame":{"_class":"rect","constrainProportions":false,"height":63.359375,"width":63.359375,"x":0,"y":0},"hasClickThrough":false,"windingRule":1}],"clippingMaskMode":0,"hasClippingMask":false,"style":{"_class":"style","fills":[],"borders":[],"shadows":[],"innerShadows":[],"endDecorationType":0,"miterLimit":10,"startDecorationType":0,"contextSettings":{"_class":"graphicsContextSettings","blendMode":0,"opacity":"1"}},"frame":{"_class":"rect","constrainProportions":false,"height":63.359375,"width":63.359375,"x":0,"y":0},"hasClickThrough":false,"windingRule":1}],"clippingMaskMode":0,"hasClippingMask":false,"style":{"_class":"style","fills":[],"borders":[],"shadows":[],"innerShadows":[],"endDecorationType":0,"miterLimit":10,"startDecorationType":0,"contextSettings":{"_class":"graphicsContextSettings","blendMode":0,"opacity":"1"}},"frame":{"_class":"rect","constrainProportions":false,"height":63.359375,"width":63.359375,"x":63.34375,"y":63.359375},"hasClickThrough":false,"windingRule":1},{"_class":"group","do_objectID":"48b06d77-db8d-4675-b646-d7794cafb1aa","exportOptions":{"_class":"exportOptions","exportFormats":[],"includedLayerIds":[],"layerOptions":0,"shouldTrim":false},"isFlippedHorizontal":false,"isFlippedVertical":false,"isLocked":false,"isVisible":true,"layerListExpandedType":0,"name":"(stellar-avatar)","nameIsFixed":false,"resizingConstraint":63,"resizingType":0,"rotation":0,"shouldBreakMaskChain":false,"layers":[],"clippingMaskMode":0,"hasClippingMask":false,"style":{"_class":"style","fills":[],"borders":[],"shadows":[],"innerShadows":[],"endDecorationType":0,"miterLimit":10,"startDecorationType":0,"contextSettings":{"_class":"graphicsContextSettings","blendMode":0,"opacity":"1"}},"frame":{"_class":"rect","constrainProportions":false,"height":126.71875,"width":126.71875,"x":126.703125,"y":0},"hasClickThrough":false,"windingRule":1},{"_class":"group","do_objectID":"17ba666e-1167-4b65-a117-73ba727085e6","exportOptions":{"_class":"exportOptions","exportFormats":[],"includedLayerIds":[],"layerOptions":0,"shouldTrim":false},"isFlippedHorizontal":false,"isFlippedVertical":false,"isLocked":false,"isVisible":true,"layerListExpandedType":0,"name":"(button)","nameIsFixed":false,"resizingConstraint":63,"resizingType":0,"rotation":0,"shouldBreakMaskChain":false,"layers":[{"_class":"group","do_objectID":"dc9b3965-6359-48f4-95fa-abbaba3fd393","exportOptions":{"_class":"exportOptions","exportFormats":[],"includedLayerIds":[],"layerOptions":0,"shouldTrim":false},"isFlippedHorizontal":false,"isFlippedVertical":false,"isLocked":false,"isVisible":true,"layerListExpandedType":0,"name":"(div)","nameIsFixed":false,"resizingConstraint":63,"resizingType":0,"rotation":0,"shouldBreakMaskChain":false,"layers":[{"_class":"group","do_objectID":"c86813ed-f598-425b-8fe9-a031910f2fa2","exportOptions":{"_class":"exportOptions","exportFormats":[],"includedLayerIds":[],"layerOptions":0,"shouldTrim":false},"isFlippedHorizontal":false,"isFlippedVertical":false,"isLocked":false,"isVisible":true,"layerListExpandedType":0,"name":"(div)","nameIsFixed":false,"resizingConstraint":63,"resizingType":0,"rotation":0,"shouldBreakMaskChain":false,"layers":[{"_class":"shapeGroup","do_objectID":"41c47cb2-ee96-4027-8463-be77920a8d19","exportOptions":{"_class":"exportOptions","exportFormats":[],"includedLayerIds":[],"layerOptions":0,"shouldTrim":false},"isFlippedHorizontal":false,"isFlippedVertical":false,"isLocked":false,"isVisible":true,"layerListExpandedType":0,"name":"/button[@class=\"wrapper\"]/div[@class=\"content\"]/div[@class=\"spacer\"]","nameIsFixed":false,"resizingConstraint":63,"resizingType":0,"rotation":0,"shouldBreakMaskChain":false,"layers":[{"_class":"rectangle","do_objectID":"3401dbf4-ff99-4712-85df-79453517bccc","exportOptions":{"_class":"exportOptions","exportFormats":[],"includedLayerIds":[],"layerOptions":0,"shouldTrim":false},"isFlippedHorizontal":false,"isFlippedVertical":false,"isLocked":false,"isVisible":true,"layerListExpandedType":0,"name":"rectangle","nameIsFixed":false,"resizingConstraint":63,"resizingType":0,"rotation":0,"shouldBreakMaskChain":false,"layers":[],"clippingMaskMode":0,"hasClippingMask":false,"frame":{"_class":"rect","constrainProportions":false,"height":126.71875,"width":126.71875,"x":0,"y":0},"path":{"_class":"path","isClosed":true,"pointRadiusBehaviour":1,"points":[{"_class":"curvePoint","cornerRadius":0,"curveFrom":"{0, 0}","curveMode":1,"curveTo":"{0, 0}","hasCurveFrom":false,"hasCurveTo":false,"point":"{0, 0}"},{"_class":"curvePoint","cornerRadius":0,"curveFrom":"{1, 0}","curveMode":1,"curveTo":"{1, 0}","hasCurveFrom":false,"hasCurveTo":false,"point":"{1, 0}"},{"_class":"curvePoint","cornerRadius":0,"curveFrom":"{1, 1}","curveMode":1,"curveTo":"{1, 1}","hasCurveFrom":false,"hasCurveTo":false,"point":"{1, 1}"},{"_class":"curvePoint","cornerRadius":0,"curveFrom":"{0, 1}","curveMode":1,"curveTo":"{0, 1}","hasCurveFrom":false,"hasCurveTo":false,"point":"{0, 1}"}]},"hasConvertedToNewRoundCorners":true,"fixedRadius":0,"edited":false,"booleanOperation":-1}],"clippingMaskMode":0,"hasClippingMask":false,"style":{"_class":"style","fills":[{"_class":"fill","isEnabled":true,"color":{"_class":"color","red":0,"green":0,"blue":0,"alpha":0},"fillType":0,"noiseIndex":0,"noiseIntensity":0,"patternFillType":1,"patternTileScale":1},{"_class":"fill","isEnabled":true,"color":{"_class":"color","alpha":1,"blue":0.847,"green":0.847,"red":0.847},"fillType":1,"gradient":{"_class":"gradient","elipseLength":0,"from":"{0.5, 0","gradientType":0,"shouldSmoothenOpacity":false,"stops":[{"_class":"gradientStop","color":{"_class":"color","red":0.792156862745098,"green":0.27450980392156865,"blue":0.29411764705882354,"alpha":1},"position":0},{"_class":"gradientStop","color":{"_class":"color","red":1,"green":0.34901960784313724,"blue":0.37254901960784315,"alpha":1},"position":1}],"to":"{0.5, 1}"},"noiseIndex":0,"noiseIntensity":0,"patternFillType":1,"patternTileScale":1}],"borders":[{"_class":"border","isEnabled":true,"color":{"_class":"color","red":0,"green":0,"blue":0,"alpha":0.8470588235294118},"fillType":0,"position":1,"thickness":0}],"shadows":[],"innerShadows":[],"endDecorationType":0,"miterLimit":10,"startDecorationType":0,"contextSettings":{"_class":"graphicsContextSettings","blendMode":0,"opacity":"1"}},"frame":{"_class":"rect","constrainProportions":false,"height":126.71875,"width":126.71875,"x":0,"y":0},"hasClickThrough":false,"windingRule":1}],"clippingMaskMode":0,"hasClippingMask":false,"style":{"_class":"style","fills":[],"borders":[],"shadows":[],"innerShadows":[],"endDecorationType":0,"miterLimit":10,"startDecorationType":0,"contextSettings":{"_class":"graphicsContextSettings","blendMode":0,"opacity":"1"}},"frame":{"_class":"rect","constrainProportions":false,"height":126.71875,"width":126.71875,"x":0,"y":0},"hasClickThrough":false,"windingRule":1},{"_class":"group","do_objectID":"5b0293f9-feeb-43a9-b0d5-25a845d08723","exportOptions":{"_class":"exportOptions","exportFormats":[],"includedLayerIds":[],"layerOptions":0,"shouldTrim":false},"isFlippedHorizontal":false,"isFlippedVertical":false,"isLocked":false,"isVisible":true,"layerListExpandedType":0,"name":"(div)","nameIsFixed":false,"resizingConstraint":63,"resizingType":0,"rotation":0,"shouldBreakMaskChain":false,"layers":[{"_class":"text","do_objectID":"5754cf21-df38-4d68-a17c-9a787ee17eaf","exportOptions":{"_class":"exportOptions","exportFormats":[],"includedLayerIds":[],"layerOptions":0,"shouldTrim":false},"isFlippedHorizontal":false,"isFlippedVertical":false,"isLocked":false,"isVisible":true,"layerListExpandedType":0,"name":"WM","nameIsFixed":false,"resizingConstraint":47,"resizingType":0,"rotation":0,"shouldBreakMaskChain":false,"clippingMaskMode":0,"hasClippingMask":false,"style":{"color":"rgb(255, 255, 255)","fontSize":57,"fontFamily":"-apple-system","fontWeight":600,"lineHeight":57,"textDecoration":"none","textAlign":"center","textTransform":"lowercase"},"frame":{"_class":"rect","constrainProportions":false,"height":68,"width":92.9375,"x":16.890625,"y":38.671875},"text":"WM","automaticallyDrawOnUnderlyingPath":false,"dontSynchroniseWithSymbol":false,"lineSpacingBehaviour":2,"textBehaviour":0}],"clippingMaskMode":0,"hasClippingMask":false,"style":{"_class":"style","fills":[],"borders":[],"shadows":[],"innerShadows":[],"endDecorationType":0,"miterLimit":10,"startDecorationType":0,"contextSettings":{"_class":"graphicsContextSettings","blendMode":0,"opacity":"1"}},"frame":{"_class":"rect","constrainProportions":false,"height":126.71875,"width":126.71875,"x":0,"y":0},"hasClickThrough":false,"windingRule":1}],"clippingMaskMode":0,"hasClippingMask":false,"style":{"_class":"style","fills":[],"borders":[],"shadows":[],"innerShadows":[],"endDecorationType":0,"miterLimit":10,"startDecorationType":0,"contextSettings":{"_class":"graphicsContextSettings","blendMode":0,"opacity":"1"}},"frame":{"_class":"rect","constrainProportions":false,"height":126.71875,"width":126.71875,"x":0,"y":0},"hasClickThrough":false,"windingRule":1}],"clippingMaskMode":0,"hasClippingMask":false,"style":{"_class":"style","fills":[],"borders":[],"shadows":[],"innerShadows":[],"endDecorationType":0,"miterLimit":10,"startDecorationType":0,"contextSettings":{"_class":"graphicsContextSettings","blendMode":0,"opacity":"1"}},"frame":{"_class":"rect","constrainProportions":false,"height":126.71875,"width":126.71875,"x":126.703125,"y":0},"hasClickThrough":false,"windingRule":1}],"clippingMaskMode":0,"hasClippingMask":false,"style":{"_class":"style","fills":[],"borders":[],"shadows":[],"innerShadows":[],"endDecorationType":0,"miterLimit":10,"startDecorationType":0,"contextSettings":{"_class":"graphicsContextSettings","blendMode":0,"opacity":"1"}},"frame":{"_class":"rect","constrainProportions":false,"height":1200,"width":1400,"x":0,"y":0},"hasClickThrough":false,"windingRule":1}],"clippingMaskMode":0,"hasClippingMask":false,"frame":{"_class":"rect","constrainProportions":false,"height":1200,"width":1400,"x":0,"y":0},"style":{"_class":"style","endDecorationType":0,"miterLimit":10,"startDecorationType":0},"horizontalRulerData":{"_class":"rulerData","base":0,"guides":[]},"verticalRulerData":{"_class":"rulerData","base":0,"guides":[]},"hasClickThrough":true,"includeInCloudUpload":true}],"clippingMaskMode":0,"hasClippingMask":false,"frame":{"_class":"rect","constrainProportions":false,"height":1200,"width":1400,"x":0,"y":0},"style":{"_class":"style","endDecorationType":0,"miterLimit":10,"startDecorationType":0},"horizontalRulerData":{"_class":"rulerData","base":0,"guides":[]},"verticalRulerData":{"_class":"rulerData","base":0,"guides":[]},"hasClickThrough":true,"includeInCloudUpload":true}