{"_class":"page","do_objectID":"569236a7-9e58-4aa0-b960-4a1b83810d7a","exportOptions":{"_class":"exportOptions","exportFormats":[],"includedLayerIds":[],"layerOptions":0,"shouldTrim":false},"isFlippedHorizontal":false,"isFlippedVertical":false,"isLocked":false,"isVisible":true,"layerListExpandedType":0,"name":"page","nameIsFixed":false,"resizingConstraint":63,"resizingType":0,"rotation":0,"shouldBreakMaskChain":false,"layers":[{"_class":"artboard","do_objectID":"332d12fb-d0b0-45e9-a2ed-90a3436e5768","exportOptions":{"_class":"exportOptions","exportFormats":[],"includedLayerIds":[],"layerOptions":0,"shouldTrim":false},"isFlippedHorizontal":false,"isFlippedVertical":false,"isLocked":false,"isVisible":true,"layerListExpandedType":0,"name":"artboard","nameIsFixed":false,"resizingConstraint":63,"resizingType":0,"rotation":0,"shouldBreakMaskChain":false,"layers":[{"_class":"group","do_objectID":"520b0565-9057-4ede-bec6-0fc4a42efa48","exportOptions":{"_class":"exportOptions","exportFormats":[],"includedLayerIds":[],"layerOptions":0,"shouldTrim":false},"isFlippedHorizontal":false,"isFlippedVertical":false,"isLocked":false,"isVisible":true,"layerListExpandedType":0,"name":"(body)","nameIsFixed":false,"resizingConstraint":63,"resizingType":0,"rotation":0,"shouldBreakMaskChain":false,"layers":[{"_class":"group","do_objectID":"a323da45-3ea6-460f-aaa7-3dbf87c1bc73","exportOptions":{"_class":"exportOptions","exportFormats":[],"includedLayerIds":[],"layerOptions":0,"shouldTrim":false},"isFlippedHorizontal":false,"isFlippedVertical":false,"isLocked":false,"isVisible":true,"layerListExpandedType":0,"name":"(stellar-blur)","nameIsFixed":false,"resizingConstraint":63,"resizingType":0,"rotation":0,"shouldBreakMaskChain":false,"layers":[{"_class":"group","do_objectID":"60c7f550-657b-4164-aac5-8cc1e011bf55","exportOptions":{"_class":"exportOptions","exportFormats":[],"includedLayerIds":[],"layerOptions":0,"shouldTrim":false},"isFlippedHorizontal":false,"isFlippedVertical":false,"isLocked":false,"isVisible":true,"layerListExpandedType":0,"name":"(h1)","nameIsFixed":false,"resizingConstraint":63,"resizingType":0,"rotation":0,"shouldBreakMaskChain":false,"layers":[{"_class":"text","do_objectID":"d6a47bdc-ad15-4830-93a3-7e66a199a086","exportOptions":{"_class":"exportOptions","exportFormats":[],"includedLayerIds":[],"layerOptions":0,"shouldTrim":false},"isFlippedHorizontal":false,"isFlippedVertical":false,"isLocked":false,"isVisible":true,"layerListExpandedType":0,"name":"Awesome!","nameIsFixed":false,"resizingConstraint":47,"resizingType":0,"rotation":0,"shouldBreakMaskChain":false,"clippingMaskMode":0,"hasClippingMask":false,"style":{"color":"rgb(45, 45, 45)","fontSize":44,"fontFamily":"-apple-system","fontWeight":400,"lineHeight":62,"textDecoration":"none","textAlign":"start","letterSpacing":0.16,"textTransform":"none"},"frame":{"_class":"rect","constrainProportions":false,"height":52,"width":201.46875,"x":0,"y":0},"text":"Awesome!","automaticallyDrawOnUnderlyingPath":false,"dontSynchroniseWithSymbol":false,"lineSpacingBehaviour":2,"textBehaviour":0}],"clippingMaskMode":0,"hasClippingMask":false,"style":{"_class":"style","fills":[],"borders":[],"shadows":[],"innerShadows":[],"endDecorationType":0,"miterLimit":10,"startDecorationType":0,"contextSettings":{"_class":"graphicsContextSettings","blendMode":0,"opacity":"1"}},"frame":{"_class":"rect","constrainProportions":false,"height":62,"width":1052.796875,"x":0,"y":0},"hasClickThrough":false,"windingRule":1}],"clippingMaskMode":0,"hasClippingMask":false,"style":{"_class":"style","fills":[],"borders":[],"shadows":[],"innerShadows":[],"endDecorationType":0,"miterLimit":10,"startDecorationType":0,"contextSettings":{"_class":"graphicsContextSettings","blendMode":0,"opacity":"1"}},"frame":{"_class":"rect","constrainProportions":false,"height":62,"width":1400,"x":0,"y":0},"hasClickThrough":false,"windingRule":1}],"clippingMaskMode":0,"hasClippingMask":false,"style":{"_class":"style","fills":[],"borders":[],"shadows":[],"innerShadows":[],"endDecorationType":0,"miterLimit":10,"startDecorationType":0,"contextSettings":{"_class":"graphicsContextSettings","blendMode":0,"opacity":"1"}},"frame":{"_class":"rect","constrainProportions":false,"height":1200,"width":1400,"x":0,"y":0},"hasClickThrough":false,"windingRule":1}],"clippingMaskMode":0,"hasClippingMask":false,"frame":{"_class":"rect","constrainProportions":false,"height":1200,"width":1400,"x":0,"y":0},"style":{"_class":"style","endDecorationType":0,"miterLimit":10,"startDecorationType":0},"horizontalRulerData":{"_class":"rulerData","base":0,"guides":[]},"verticalRulerData":{"_class":"rulerData","base":0,"guides":[]},"hasClickThrough":true,"includeInCloudUpload":true}],"clippingMaskMode":0,"hasClippingMask":false,"frame":{"_class":"rect","constrainProportions":false,"height":1200,"width":1400,"x":0,"y":0},"style":{"_class":"style","endDecorationType":0,"miterLimit":10,"startDecorationType":0},"horizontalRulerData":{"_class":"rulerData","base":0,"guides":[]},"verticalRulerData":{"_class":"rulerData","base":0,"guides":[]},"hasClickThrough":true,"includeInCloudUpload":true}